CHANGELOG.md
CODE_OF_CONDUCT.md
CONTRIBUTING.md
CONTRIBUTORS.md
ESTIMATOR_OVERVIEW.md
GOVERNANCE.md
LICENSE
MANIFEST.in
README.md
estimator_overview_table.md
pyproject.toml
setup.cfg
build_tools/changelog.py
build_tools/make_release.py
docs/Makefile
docs/make.bat
docs/symlink_examples.sh
docs/source/about.rst
docs/source/api_reference.rst
docs/source/changelog.rst
docs/source/conf.py
docs/source/developer_guide.rst
docs/source/developers.rst
docs/source/estimator_overview.md
docs/source/examples.rst
docs/source/get_involved.rst
docs/source/get_started.rst
docs/source/glossary.rst
docs/source/index.rst
docs/source/installation.rst
docs/source/related_software.rst
docs/source/roadmap.rst
docs/source/tutorials.rst
docs/source/user_guide.rst
docs/source/users.rst
docs/source/_static/css/custom.css
docs/source/_static/css/fields.css
docs/source/_static/js/dynamic_table.js
docs/source/_templates/class.rst
docs/source/_templates/class_with_call.rst
docs/source/_templates/function.rst
docs/source/_templates/layout.html
docs/source/_templates/numpydoc_docstring.rst
docs/source/about/_mission.rst
docs/source/about/artwork.rst
docs/source/about/citation.md
docs/source/about/contributors.md
docs/source/about/funding.rst
docs/source/about/history.rst
docs/source/about/mission.rst
docs/source/about/showcase.rst
docs/source/about/team.rst
docs/source/api_reference/annotation.rst
docs/source/api_reference/base.rst
docs/source/api_reference/classification.rst
docs/source/api_reference/clustering.rst
docs/source/api_reference/data_format.rst
docs/source/api_reference/datasets.rst
docs/source/api_reference/deployment.rst
docs/source/api_reference/dists_kernels.rst
docs/source/api_reference/exceptions.rst
docs/source/api_reference/forecasting.rst
docs/source/api_reference/performance_metrics.rst
docs/source/api_reference/regression.rst
docs/source/api_reference/series_as_features.rst
docs/source/api_reference/transformations.rst
docs/source/api_reference/utils.rst
sktime_backup.egg-info/PKG-INFO
sktime_backup.egg-info/SOURCES.txt
sktime_backup.egg-info/dependency_links.txt
sktime_backup.egg-info/requires.txt
sktime_backup.egg-info/top_level.txt
sktime_backup.egg-info/zip-safe