Metadata-Version: 2.1
Name: sktime-backup
Version: 0.16.1
Summary: A unified framework for machine learning with time series
Author-email: sktime developers <sktime.toolbox@gmail.com>
Maintainer-email: sktime developers <sktime.toolbox@gmail.com>, Franz Király <f.kiraly@ucl.ac.uk>
License: BSD 3-Clause License
Project-URL: Homepage, https://www.sktime.org
Project-URL: Repository, https://github.com/sktime/sktime
Project-URL: Documentation, https://www.sktime.org
Project-URL: Download, https://pypi.org/project/sktime/#files
Project-URL: API Reference, https://www.sktime.org/en/stable/api_reference.html
Project-URL: Release Notes, https://www.sktime.org/en/stable/changelog.html
Keywords: data-science,machine-learning,data-mining,time-series,scikit-learn,forecasting,time-series-analysis,time-series-classification,time-series-regression
Classifier: Intended Audience :: Science/Research
Classifier: Intended Audience :: Developers
Classifier: License :: OSI Approved :: BSD License
Classifier: Programming Language :: Python
Classifier: Topic :: Software Development
Classifier: Topic :: Scientific/Engineering
Classifier: Operating System :: Microsoft :: Windows
Classifier: Operating System :: POSIX
Classifier: Operating System :: Unix
Classifier: Operating System :: MacOS
Classifier: Programming Language :: Python :: 3.7
Classifier: Programming Language :: Python :: 3.8
Classifier: Programming Language :: Python :: 3.9
Classifier: Programming Language :: Python :: 3.10
Classifier: Programming Language :: Python :: 3.11
Requires-Python: <3.12,>=3.7
Provides-Extra: all_extras
Provides-Extra: dev
Provides-Extra: mlflow
Provides-Extra: mlflow_tests
Provides-Extra: binder
Provides-Extra: docs
Provides-Extra: dl
License-File: LICENSE
